{
"meta":{"test_sets":[],"test_metrics":[],"learn_metrics":[{"best_value":"Min","name":"RMSE"}],"launch_mode":"Train","parameters":"","iteration_count":300,"learn_sets":["learn"],"name":"experiment"},
"iterations":[
{"learn":[11174370.81],"iteration":0,"passed_time":0.01015629937,"remaining_time":3.036733513},
{"learn":[10711612.43],"iteration":1,"passed_time":0.0168448397,"remaining_time":2.509881116},
{"learn":[10255838.27],"iteration":2,"passed_time":0.02281650327,"remaining_time":2.258833824},
{"learn":[9832932.903],"iteration":3,"passed_time":0.02961531477,"remaining_time":2.191533293},
{"learn":[9431875.987],"iteration":4,"passed_time":0.03640271443,"remaining_time":2.147760151},
{"learn":[9045118.735],"iteration":5,"passed_time":0.04344023967,"remaining_time":2.128571744},
{"learn":[8679553.922],"iteration":6,"passed_time":0.05094879313,"remaining_time":2.132570913},
{"learn":[8343112.309],"iteration":7,"passed_time":0.05768862884,"remaining_time":2.105634953},
{"learn":[8017441.527],"iteration":8,"passed_time":0.06511962801,"remaining_time":2.105534639},
{"learn":[7703156.151],"iteration":9,"passed_time":0.07374516893,"remaining_time":2.138609899},
{"learn":[7412798.869],"iteration":10,"passed_time":0.08156341428,"remaining_time":2.142893339},
{"learn":[7133335.019],"iteration":11,"passed_time":0.08979305249,"remaining_time":2.15503326},
{"learn":[6872542.975],"iteration":12,"passed_time":0.097838231,"remaining_time":2.1599671},
{"learn":[6624311.077],"iteration":13,"passed_time":0.1051729581,"remaining_time":2.148533287},
{"learn":[6398951.033],"iteration":14,"passed_time":0.1132450052,"remaining_time":2.151655099},
{"learn":[6182581.964],"iteration":15,"passed_time":0.1202505629,"remaining_time":2.134447492},
{"learn":[5988706.172],"iteration":16,"passed_time":0.1280317395,"remaining_time":2.131351899},
{"learn":[5796113.676],"iteration":17,"passed_time":0.1351381153,"remaining_time":2.117163807},
{"learn":[5618042.258],"iteration":18,"passed_time":0.1432791132,"remaining_time":2.119022674},
{"learn":[5441920.659],"iteration":19,"passed_time":0.1508064093,"remaining_time":2.111289731},
{"learn":[5280280.825],"iteration":20,"passed_time":0.1590185829,"remaining_time":2.112675459},
{"learn":[5124021.308],"iteration":21,"passed_time":0.1664165556,"remaining_time":2.102900111},
{"learn":[4978257.894],"iteration":22,"passed_time":0.1744823243,"remaining_time":2.101374079},
{"learn":[4841784.556],"iteration":23,"passed_time":0.1829725572,"remaining_time":2.104184408},
{"learn":[4701875.483],"iteration":24,"passed_time":0.1921265512,"remaining_time":2.113392064},
{"learn":[4579658.736],"iteration":25,"passed_time":0.1996728871,"remaining_time":2.104245041},
{"learn":[4466219.761],"iteration":26,"passed_time":0.2084341347,"remaining_time":2.107500695},
{"learn":[4357557.808],"iteration":27,"passed_time":0.2157166264,"remaining_time":2.095532942},
{"learn":[4246072.277],"iteration":28,"passed_time":0.2241976717,"remaining_time":2.095088587},
{"learn":[4139838.418],"iteration":29,"passed_time":0.2328786657,"remaining_time":2.095907992},
{"learn":[4037434.721],"iteration":30,"passed_time":0.2422631674,"remaining_time":2.102219098},
{"learn":[3946815.343],"iteration":31,"passed_time":0.2508947926,"remaining_time":2.101243888},
{"learn":[3859140.278],"iteration":32,"passed_time":0.2594256818,"remaining_time":2.098989607},
{"learn":[3781635.626],"iteration":33,"passed_time":0.2674358175,"remaining_time":2.092291984},
{"learn":[3707644.843],"iteration":34,"passed_time":0.2762817726,"remaining_time":2.091847707},
{"learn":[3643613.209],"iteration":35,"passed_time":0.2840590915,"remaining_time":2.083100004},
{"learn":[3576433.42],"iteration":36,"passed_time":0.2937019774,"remaining_time":2.087665407},
{"learn":[3504530.697],"iteration":37,"passed_time":0.3033980991,"remaining_time":2.091850052},
{"learn":[3443988.327],"iteration":38,"passed_time":0.3124809577,"remaining_time":2.091218717},
{"learn":[3384258.183],"iteration":39,"passed_time":0.3216225814,"remaining_time":2.090546779},
{"learn":[3335369.12],"iteration":40,"passed_time":0.3297892423,"remaining_time":2.083302774},
{"learn":[3290130.678],"iteration":41,"passed_time":0.3385171575,"remaining_time":2.079462539},
{"learn":[3245218.067],"iteration":42,"passed_time":0.3472291591,"remaining_time":2.075299858},
{"learn":[3195006.245],"iteration":43,"passed_time":0.3567586939,"remaining_time":2.075686946},
{"learn":[3148958.589],"iteration":44,"passed_time":0.3663791341,"remaining_time":2.076148427},
{"learn":[3110444.524],"iteration":45,"passed_time":0.3753346348,"remaining_time":2.07249994},
{"learn":[3074219.07],"iteration":46,"passed_time":0.3847105134,"remaining_time":2.070888508},
{"learn":[3041342.409],"iteration":47,"passed_time":0.3930722116,"remaining_time":2.063629111},
{"learn":[2999565.978],"iteration":48,"passed_time":0.4023703375,"remaining_time":2.061121525},
{"learn":[2961483.581],"iteration":49,"passed_time":0.4110539836,"remaining_time":2.055269918},
{"learn":[2928461.887],"iteration":50,"passed_time":0.4192691051,"remaining_time":2.047019748},
{"learn":[2898257.834],"iteration":51,"passed_time":0.427450801,"remaining_time":2.038611513},
{"learn":[2869381.295],"iteration":52,"passed_time":0.4359719908,"remaining_time":2.031793995},
{"learn":[2846421.821],"iteration":53,"passed_time":0.4445641537,"remaining_time":2.0252367},
{"learn":[2814169.764],"iteration":54,"passed_time":0.4528970626,"remaining_time":2.017450552},
{"learn":[2792052.698],"iteration":55,"passed_time":0.460597351,"remaining_time":2.006888458},
{"learn":[2772857.6],"iteration":56,"passed_time":0.4694064637,"remaining_time":2.001153872},
{"learn":[2752235.649],"iteration":57,"passed_time":0.4765774031,"remaining_time":1.98847813},
{"learn":[2729072.901],"iteration":58,"passed_time":0.4855399124,"remaining_time":1.9833071},
{"learn":[2703956.399],"iteration":59,"passed_time":0.4932939733,"remaining_time":1.973175893},
{"learn":[2678656.153],"iteration":60,"passed_time":0.5022394768,"remaining_time":1.967790737},
{"learn":[2654385.9],"iteration":61,"passed_time":0.5109263302,"remaining_time":1.961297848},
{"learn":[2639222.041],"iteration":62,"passed_time":0.5184349439,"remaining_time":1.950302884},
{"learn":[2624182.553],"iteration":63,"passed_time":0.5267799726,"remaining_time":1.942501149},
{"learn":[2610162.422],"iteration":64,"passed_time":0.534598394,"remaining_time":1.932778809},
{"learn":[2586472.991],"iteration":65,"passed_time":0.5440531886,"remaining_time":1.928915851},
{"learn":[2570085.593],"iteration":66,"passed_time":0.5535951379,"remaining_time":1.925189062},
{"learn":[2552241.819],"iteration":67,"passed_time":0.5640247603,"remaining_time":1.92431977},
{"learn":[2534219.999],"iteration":68,"passed_time":0.5732977346,"remaining_time":1.919301111},
{"learn":[2512973.874],"iteration":69,"passed_time":0.5824042575,"remaining_time":1.913613989},
{"learn":[2500223.889],"iteration":70,"passed_time":0.5911349358,"remaining_time":1.906618314},
{"learn":[2486368.732],"iteration":71,"passed_time":0.5996060772,"remaining_time":1.898752578},
{"learn":[2471940.037],"iteration":72,"passed_time":0.6080155992,"remaining_time":1.890678644},
{"learn":[2452328.464],"iteration":73,"passed_time":0.6171671682,"remaining_time":1.884861892},
{"learn":[2433557.788],"iteration":74,"passed_time":0.6260714127,"remaining_time":1.878214238},
{"learn":[2423068.049],"iteration":75,"passed_time":0.6332412129,"remaining_time":1.866395154},
{"learn":[2411330.09],"iteration":76,"passed_time":0.6413832091,"remaining_time":1.857512411},
{"learn":[2390948.79],"iteration":77,"passed_time":0.6489695919,"remaining_time":1.8470673},
{"learn":[2380677.978],"iteration":78,"passed_time":0.6569937344,"remaining_time":1.837919181},
{"learn":[2367649.218],"iteration":79,"passed_time":0.6645503421,"remaining_time":1.827513441},
{"learn":[2353042.812],"iteration":80,"passed_time":0.6729653931,"remaining_time":1.819499026},
{"learn":[2339429.874],"iteration":81,"passed_time":0.6807542759,"remaining_time":1.809810148},
{"learn":[2330198.346],"iteration":82,"passed_time":0.6891897786,"remaining_time":1.801857614},
{"learn":[2317953.303],"iteration":83,"passed_time":0.6974882681,"remaining_time":1.793541261},
{"learn":[2304185.476],"iteration":84,"passed_time":0.7071997329,"remaining_time":1.788799324},
{"learn":[2291883.091],"iteration":85,"passed_time":0.7157301932,"remaining_time":1.781003039},
{"learn":[2281848.905],"iteration":86,"passed_time":0.7264076562,"remaining_time":1.778446331},
{"learn":[2270993.075],"iteration":87,"passed_time":0.7367468268,"remaining_time":1.774890083},
{"learn":[2262002.007],"iteration":88,"passed_time":0.7440967167,"remaining_time":1.764094463},
{"learn":[2249267.539],"iteration":89,"passed_time":0.7528228854,"remaining_time":1.756586733},
{"learn":[2239985.083],"iteration":90,"passed_time":0.7609195627,"remaining_time":1.747606468},
{"learn":[2231010.914],"iteration":91,"passed_time":0.7689742894,"remaining_time":1.738550567},
{"learn":[2216435.235],"iteration":92,"passed_time":0.7792910603,"remaining_time":1.73455107},
{"learn":[2201145.501],"iteration":93,"passed_time":0.7894329719,"remaining_time":1.73003396},
{"learn":[2195156.858],"iteration":94,"passed_time":0.7973598857,"remaining_time":1.720618701},
{"learn":[2186362.417],"iteration":95,"passed_time":0.8063354276,"remaining_time":1.713462784},
{"learn":[2171548.298],"iteration":96,"passed_time":0.8162216093,"remaining_time":1.708175121},
{"learn":[2158082.951],"iteration":97,"passed_time":0.82560175,"remaining_time":1.701750546},
{"learn":[2148619.423],"iteration":98,"passed_time":0.8353626278,"remaining_time":1.696039275},
{"learn":[2140852.505],"iteration":99,"passed_time":0.8442261542,"remaining_time":1.688452308},
{"learn":[2127850.11],"iteration":100,"passed_time":0.8679110944,"remaining_time":1.710042651},
{"learn":[2123395.933],"iteration":101,"passed_time":0.8793415376,"remaining_time":1.706957102},
{"learn":[2109510.411],"iteration":102,"passed_time":0.8906097213,"remaining_time":1.703399176},
{"learn":[2099104.181],"iteration":103,"passed_time":0.8996008645,"remaining_time":1.695401629},
{"learn":[2082272.855],"iteration":104,"passed_time":0.9068116521,"remaining_time":1.684078782},
{"learn":[2076235.561],"iteration":105,"passed_time":0.9157409031,"remaining_time":1.675978634},
{"learn":[2062659.873],"iteration":106,"passed_time":0.9230233863,"remaining_time":1.66489265},
{"learn":[2057520.324],"iteration":107,"passed_time":0.9317516934,"remaining_time":1.656447455},
{"learn":[2049430.93],"iteration":108,"passed_time":0.9393815216,"remaining_time":1.646072208},
{"learn":[2038943.312],"iteration":109,"passed_time":0.9485723392,"remaining_time":1.638443131},
{"learn":[2032259.449],"iteration":110,"passed_time":0.9558025981,"remaining_time":1.627447667},
{"learn":[2024437.643],"iteration":111,"passed_time":0.9651524146,"remaining_time":1.620077267},
{"learn":[2017885.779],"iteration":112,"passed_time":0.9727695065,"remaining_time":1.609804405},
{"learn":[2011953.57],"iteration":113,"passed_time":0.9815642656,"remaining_time":1.601499591},
{"learn":[1999144.357],"iteration":114,"passed_time":0.9897557979,"remaining_time":1.592215849},
{"learn":[1992452.335],"iteration":115,"passed_time":0.9978201803,"remaining_time":1.582749252},
{"learn":[1984705.106],"iteration":116,"passed_time":1.007379844,"remaining_time":1.575645397},
{"learn":[1980052.293],"iteration":117,"passed_time":1.018888322,"remaining_time":1.571505716},
{"learn":[1973611.557],"iteration":118,"passed_time":1.030151119,"remaining_time":1.566868509},
{"learn":[1965290.557],"iteration":119,"passed_time":1.037896498,"remaining_time":1.556844747},
{"learn":[1958894.147],"iteration":120,"passed_time":1.0478137,"remaining_time":1.550071507},
{"learn":[1950338.618],"iteration":121,"passed_time":1.057675091,"remaining_time":1.543165296},
{"learn":[1939823.842],"iteration":122,"passed_time":1.066290109,"remaining_time":1.534417474},
{"learn":[1933256.784],"iteration":123,"passed_time":1.076662732,"remaining_time":1.528166458},
{"learn":[1927168.871],"iteration":124,"passed_time":1.08625355,"remaining_time":1.52075497},
{"learn":[1918890.433],"iteration":125,"passed_time":1.095956912,"remaining_time":1.513464307},
{"learn":[1909253.965],"iteration":126,"passed_time":1.105341443,"remaining_time":1.505701336},
{"learn":[1905771.034],"iteration":127,"passed_time":1.113526019,"remaining_time":1.496300588},
{"learn":[1900083.616],"iteration":128,"passed_time":1.121785007,"remaining_time":1.487017335},
{"learn":[1893107.912],"iteration":129,"passed_time":1.130240332,"remaining_time":1.478006588},
{"learn":[1884569.308],"iteration":130,"passed_time":1.138233266,"remaining_time":1.468407801},
{"learn":[1873382.219],"iteration":131,"passed_time":1.146593967,"remaining_time":1.459301413},
{"learn":[1865493.093],"iteration":132,"passed_time":1.154834433,"remaining_time":1.450055266},
{"learn":[1859757.2],"iteration":133,"passed_time":1.162900228,"remaining_time":1.440607745},
{"learn":[1856598.426],"iteration":134,"passed_time":1.171265847,"remaining_time":1.431547147},
{"learn":[1847591.165],"iteration":135,"passed_time":1.17940993,"remaining_time":1.422229622},
{"learn":[1839511.119],"iteration":136,"passed_time":1.188429078,"remaining_time":1.413970363},
{"learn":[1831784.522],"iteration":137,"passed_time":1.197760186,"remaining_time":1.406066305},
{"learn":[1827015.698],"iteration":138,"passed_time":1.206690657,"remaining_time":1.397677667},
{"learn":[1819457.925],"iteration":139,"passed_time":1.214265711,"remaining_time":1.387732241},
{"learn":[1809731.146],"iteration":140,"passed_time":1.223001303,"remaining_time":1.379129129},
{"learn":[1800862.694],"iteration":141,"passed_time":1.230933808,"remaining_time":1.369630575},
{"learn":[1794703.332],"iteration":142,"passed_time":1.239509065,"remaining_time":1.360859603},
{"learn":[1788764.748],"iteration":143,"passed_time":1.246994694,"remaining_time":1.350910919},
{"learn":[1782702.044],"iteration":144,"passed_time":1.256905779,"remaining_time":1.343588936},
{"learn":[1776775.245],"iteration":145,"passed_time":1.266603028,"remaining_time":1.336005934},
{"learn":[1770326.406],"iteration":146,"passed_time":1.275418063,"remaining_time":1.327475943},
{"learn":[1761644.739],"iteration":147,"passed_time":1.282986627,"remaining_time":1.317661941},
{"learn":[1755203.152],"iteration":148,"passed_time":1.2911598,"remaining_time":1.308490804},
{"learn":[1751308.385],"iteration":149,"passed_time":1.299054122,"remaining_time":1.299054122},
{"learn":[1743510.241],"iteration":150,"passed_time":1.307203695,"remaining_time":1.289889739},
{"learn":[1734801.944],"iteration":151,"passed_time":1.314593848,"remaining_time":1.279999273},
{"learn":[1728627.697],"iteration":152,"passed_time":1.322800278,"remaining_time":1.270925757},
{"learn":[1724566.506],"iteration":153,"passed_time":1.330153366,"remaining_time":1.26105449},
{"learn":[1717605.08],"iteration":154,"passed_time":1.33925479,"remaining_time":1.252851256},
{"learn":[1713648.358],"iteration":155,"passed_time":1.347155638,"remaining_time":1.243528281},
{"learn":[1709223.174],"iteration":156,"passed_time":1.356435688,"remaining_time":1.235479639},
{"learn":[1705714.839],"iteration":157,"passed_time":1.365421706,"remaining_time":1.227151153},
{"learn":[1700144.294],"iteration":158,"passed_time":1.372975647,"remaining_time":1.217544442},
{"learn":[1694831.459],"iteration":159,"passed_time":1.381470285,"remaining_time":1.2087865},
{"learn":[1691596.849],"iteration":160,"passed_time":1.388692932,"remaining_time":1.19893365},
{"learn":[1686726.852],"iteration":161,"passed_time":1.397187962,"remaining_time":1.190197153},
{"learn":[1683226.914],"iteration":162,"passed_time":1.404427624,"remaining_time":1.180408494},
{"learn":[1680258.316],"iteration":163,"passed_time":1.411619451,"remaining_time":1.170611252},
{"learn":[1675340.342],"iteration":164,"passed_time":1.418808981,"remaining_time":1.160843711},
{"learn":[1670266.892],"iteration":165,"passed_time":1.425925191,"remaining_time":1.151048046},
{"learn":[1667507.471],"iteration":166,"passed_time":1.43391103,"remaining_time":1.141977048},
{"learn":[1664090.261],"iteration":167,"passed_time":1.441004776,"remaining_time":1.132218038},
{"learn":[1660307.125],"iteration":168,"passed_time":1.448268753,"remaining_time":1.122622525},
{"learn":[1655272.888],"iteration":169,"passed_time":1.455436035,"remaining_time":1.112980497},
{"learn":[1652364.294],"iteration":170,"passed_time":1.462629093,"remaining_time":1.103386859},
{"learn":[1647631.42],"iteration":171,"passed_time":1.469607973,"remaining_time":1.093661747},
{"learn":[1641254.67],"iteration":172,"passed_time":1.47714915,"remaining_time":1.084381168},
{"learn":[1631870.273],"iteration":173,"passed_time":1.484014578,"remaining_time":1.074631246},
{"learn":[1627217.138],"iteration":174,"passed_time":1.491028082,"remaining_time":1.065020058},
{"learn":[1618969.079],"iteration":175,"passed_time":1.498344429,"remaining_time":1.055651757},
{"learn":[1614111.589],"iteration":176,"passed_time":1.506171329,"remaining_time":1.046661432},
{"learn":[1607391.253],"iteration":177,"passed_time":1.514099779,"remaining_time":1.037753781},
{"learn":[1602493.234],"iteration":178,"passed_time":1.521728703,"remaining_time":1.028654598},
{"learn":[1599251.709],"iteration":179,"passed_time":1.528783221,"remaining_time":1.019188814},
{"learn":[1596389.037],"iteration":180,"passed_time":1.535364737,"remaining_time":1.009438694},
{"learn":[1590393.389],"iteration":181,"passed_time":1.542472623,"remaining_time":1.000064668},
{"learn":[1585687.331],"iteration":182,"passed_time":1.550483598,"remaining_time":0.991292792},
{"learn":[1581004.246],"iteration":183,"passed_time":1.557603666,"remaining_time":0.9819675284},
{"learn":[1573354.207],"iteration":184,"passed_time":1.564752563,"remaining_time":0.9726840254},
{"learn":[1565478.991],"iteration":185,"passed_time":1.572211776,"remaining_time":0.9636136694},
{"learn":[1561686.421],"iteration":186,"passed_time":1.581300251,"remaining_time":0.9555450715},
{"learn":[1558647.354],"iteration":187,"passed_time":1.590990922,"remaining_time":0.9478243793},
{"learn":[1553193.05],"iteration":188,"passed_time":1.599570023,"remaining_time":0.9394300134},
{"learn":[1549622.445],"iteration":189,"passed_time":1.608570207,"remaining_time":0.9312774885},
{"learn":[1546030.572],"iteration":190,"passed_time":1.617319322,"remaining_time":0.9229728067},
{"learn":[1540721.596],"iteration":191,"passed_time":1.626414103,"remaining_time":0.9148579329},
{"learn":[1536945.354],"iteration":192,"passed_time":1.634089698,"remaining_time":0.9059461019},
{"learn":[1531143.766],"iteration":193,"passed_time":1.643507951,"remaining_time":0.8979991897},
{"learn":[1527213.64],"iteration":194,"passed_time":1.651509555,"remaining_time":0.8892743756},
{"learn":[1523180.661],"iteration":195,"passed_time":1.659954588,"remaining_time":0.8807922306},
{"learn":[1519526.922],"iteration":196,"passed_time":1.667541435,"remaining_time":0.8718617654},
{"learn":[1516851.362],"iteration":197,"passed_time":1.676446355,"remaining_time":0.86362388},
{"learn":[1514484.564],"iteration":198,"passed_time":1.683939672,"remaining_time":0.8546628484},
{"learn":[1509837.635],"iteration":199,"passed_time":1.691710227,"remaining_time":0.8458551137},
{"learn":[1504970.767],"iteration":200,"passed_time":1.698547345,"remaining_time":0.8365979459},
{"learn":[1501729.736],"iteration":201,"passed_time":1.707351865,"remaining_time":0.8283192218},
{"learn":[1497422.405],"iteration":202,"passed_time":1.714599947,"remaining_time":0.8192916001},
{"learn":[1493323.736],"iteration":203,"passed_time":1.722991042,"remaining_time":0.8108193137},
{"learn":[1491129.193],"iteration":204,"passed_time":1.729893517,"remaining_time":0.8016579713},
{"learn":[1485199.9],"iteration":205,"passed_time":1.738586472,"remaining_time":0.7933355746},
{"learn":[1481419.719],"iteration":206,"passed_time":1.745540076,"remaining_time":0.78422815},
{"learn":[1476221.243],"iteration":207,"passed_time":1.754124675,"remaining_time":0.775862837},
{"learn":[1472473.672],"iteration":208,"passed_time":1.761592102,"remaining_time":0.7670090014},
{"learn":[1465481.783],"iteration":209,"passed_time":1.769725798,"remaining_time":0.7584539134},
{"learn":[1462207.496],"iteration":210,"passed_time":1.77683865,"remaining_time":0.7494722268},
{"learn":[1458772.727],"iteration":211,"passed_time":1.78629248,"remaining_time":0.7414798975},
{"learn":[1453856.222],"iteration":212,"passed_time":1.79412765,"remaining_time":0.732812702},
{"learn":[1450276.616],"iteration":213,"passed_time":1.802606424,"remaining_time":0.7244119274},
{"learn":[1447029.824],"iteration":214,"passed_time":1.810111837,"remaining_time":0.71562561},
{"learn":[1442107.35],"iteration":215,"passed_time":1.818388641,"remaining_time":0.7071511381},
{"learn":[1438334.704],"iteration":216,"passed_time":1.825468913,"remaining_time":0.6982208284},
{"learn":[1436193.676],"iteration":217,"passed_time":1.83367198,"remaining_time":0.6897298274},
{"learn":[1430763.759],"iteration":218,"passed_time":1.840795423,"remaining_time":0.6808421429},
{"learn":[1424546.827],"iteration":219,"passed_time":1.848456142,"remaining_time":0.6721658697},
{"learn":[1419693.915],"iteration":220,"passed_time":1.855927068,"remaining_time":0.6634309428},
{"learn":[1415409.538],"iteration":221,"passed_time":1.863935709,"remaining_time":0.6548963302},
{"learn":[1412601.586],"iteration":222,"passed_time":1.870661336,"remaining_time":0.6459234211},
{"learn":[1409556.52],"iteration":223,"passed_time":1.878642875,"remaining_time":0.6373966896},
{"learn":[1406424.572],"iteration":224,"passed_time":1.88702547,"remaining_time":0.6290084899},
{"learn":[1400812.448],"iteration":225,"passed_time":1.89599208,"remaining_time":0.6208115661},
{"learn":[1396603.081],"iteration":226,"passed_time":1.903524881,"remaining_time":0.6121467677},
{"learn":[1393159.99],"iteration":227,"passed_time":1.911290362,"remaining_time":0.6035653774},
{"learn":[1390595.936],"iteration":228,"passed_time":1.918862799,"remaining_time":0.5949312609},
{"learn":[1385327.378],"iteration":229,"passed_time":1.927606107,"remaining_time":0.5866627281},
{"learn":[1380142.941],"iteration":230,"passed_time":1.934604642,"remaining_time":0.5778689191},
{"learn":[1375584.77],"iteration":231,"passed_time":1.941476391,"remaining_time":0.5690534248},
{"learn":[1372403.048],"iteration":232,"passed_time":1.948483766,"remaining_time":0.5602936152},
{"learn":[1369961.668],"iteration":233,"passed_time":1.956570045,"remaining_time":0.5518530895},
{"learn":[1367568.206],"iteration":234,"passed_time":1.965638372,"remaining_time":0.5436872092},
{"learn":[1361723.067],"iteration":235,"passed_time":1.975658452,"remaining_time":0.5357717835},
{"learn":[1359583.668],"iteration":236,"passed_time":1.983112845,"remaining_time":0.5271565789},
{"learn":[1356069.174],"iteration":237,"passed_time":1.991424989,"remaining_time":0.518774577},
{"learn":[1352557.69],"iteration":238,"passed_time":1.998565515,"remaining_time":0.5100941272},
{"learn":[1350558.533],"iteration":239,"passed_time":2.006923608,"remaining_time":0.501730902},
{"learn":[1346805.092],"iteration":240,"passed_time":2.015514811,"remaining_time":0.4934247877},
{"learn":[1343553.483],"iteration":241,"passed_time":2.024566732,"remaining_time":0.4852267374},
{"learn":[1339606.478],"iteration":242,"passed_time":2.032554041,"remaining_time":0.4767719356},
{"learn":[1337740.705],"iteration":243,"passed_time":2.04171466,"remaining_time":0.4685902498},
{"learn":[1333349.498],"iteration":244,"passed_time":2.049689532,"remaining_time":0.4601343847},
{"learn":[1328575.635],"iteration":245,"passed_time":2.057983982,"remaining_time":0.4517525814},
{"learn":[1325588.029],"iteration":246,"passed_time":2.06673944,"remaining_time":0.4434704061},
{"learn":[1321980.708],"iteration":247,"passed_time":2.07628106,"remaining_time":0.4353492545},
{"learn":[1318653.03],"iteration":248,"passed_time":2.085790718,"remaining_time":0.427210147},
{"learn":[1313737.515],"iteration":249,"passed_time":2.093930327,"remaining_time":0.4187860654},
{"learn":[1307605.368],"iteration":250,"passed_time":2.103201848,"remaining_time":0.4105852214},
{"learn":[1304805.294],"iteration":251,"passed_time":2.113007387,"remaining_time":0.4024775975},
{"learn":[1300397.478],"iteration":252,"passed_time":2.124209794,"remaining_time":0.3946160487},
{"learn":[1296662.147],"iteration":253,"passed_time":2.134263252,"remaining_time":0.3865201166},
{"learn":[1293852.277],"iteration":254,"passed_time":2.143623961,"remaining_time":0.3782865814},
{"learn":[1291317.82],"iteration":255,"passed_time":2.153336011,"remaining_time":0.3701046269},
{"learn":[1288207.993],"iteration":256,"passed_time":2.161822367,"remaining_time":0.3617056879},
{"learn":[1285590.412],"iteration":257,"passed_time":2.17188234,"remaining_time":0.3535622415},
{"learn":[1282365.094],"iteration":258,"passed_time":2.180221996,"remaining_time":0.3451316673},
{"learn":[1278443.268],"iteration":259,"passed_time":2.190059878,"remaining_time":0.3369322889},
{"learn":[1276068.437],"iteration":260,"passed_time":2.200812386,"remaining_time":0.3288570232},
{"learn":[1271995.22],"iteration":261,"passed_time":2.209764062,"remaining_time":0.3205001311},
{"learn":[1266510.308],"iteration":262,"passed_time":2.219485675,"remaining_time":0.3122470342},
{"learn":[1261028.85],"iteration":263,"passed_time":2.230067832,"remaining_time":0.304100159},
{"learn":[1258669.321],"iteration":264,"passed_time":2.238570137,"remaining_time":0.2956602068},
{"learn":[1255433.322],"iteration":265,"passed_time":2.248805766,"remaining_time":0.2874413385},
{"learn":[1252886.046],"iteration":266,"passed_time":2.256876232,"remaining_time":0.278939759},
{"learn":[1249016.134],"iteration":267,"passed_time":2.266661156,"remaining_time":0.2706461082},
{"learn":[1245958.094],"iteration":268,"passed_time":2.275876103,"remaining_time":0.2622756848},
{"learn":[1243161.451],"iteration":269,"passed_time":2.286669524,"remaining_time":0.2540743916},
{"learn":[1240942.472],"iteration":270,"passed_time":2.2975446,"remaining_time":0.2458627063},
{"learn":[1238186.26],"iteration":271,"passed_time":2.307861995,"remaining_time":0.2375740289},
{"learn":[1235079.19],"iteration":272,"passed_time":2.318560615,"remaining_time":0.2293081927},
{"learn":[1233543.224],"iteration":273,"passed_time":2.328377225,"remaining_time":0.2209409046},
{"learn":[1229673.467],"iteration":274,"passed_time":2.338320982,"remaining_time":0.2125746347},
{"learn":[1225291.307],"iteration":275,"passed_time":2.34929822,"remaining_time":0.2042868017},
{"learn":[1221904.878],"iteration":276,"passed_time":2.361027367,"remaining_time":0.1960419835},
{"learn":[1218443.099],"iteration":277,"passed_time":2.370766339,"remaining_time":0.1876146024},
{"learn":[1216590.373],"iteration":278,"passed_time":2.381180201,"remaining_time":0.1792286172},
{"learn":[1213197.767],"iteration":279,"passed_time":2.391308674,"remaining_time":0.1708077624},
{"learn":[1211438.889],"iteration":280,"passed_time":2.400874147,"remaining_time":0.1623366861},
{"learn":[1208201.008],"iteration":281,"passed_time":2.410271299,"remaining_time":0.1538471042},
{"learn":[1204073.112],"iteration":282,"passed_time":2.418610113,"remaining_time":0.1452875333},
{"learn":[1201962.224],"iteration":283,"passed_time":2.427602069,"remaining_time":0.1367663137},
{"learn":[1199747.738],"iteration":284,"passed_time":2.436373226,"remaining_time":0.1282301698},
{"learn":[1197597.246],"iteration":285,"passed_time":2.445923994,"remaining_time":0.1197305452},
{"learn":[1194605.219],"iteration":286,"passed_time":2.455322696,"remaining_time":0.1112167075},
{"learn":[1192104.909],"iteration":287,"passed_time":2.464412797,"remaining_time":0.1026838666},
{"learn":[1187478.475],"iteration":288,"passed_time":2.473469018,"remaining_time":0.09414587959},
{"learn":[1184726.113],"iteration":289,"passed_time":2.481356434,"remaining_time":0.08556401496},
{"learn":[1181821.844],"iteration":290,"passed_time":2.491201803,"remaining_time":0.07704747844},
{"learn":[1179951.883],"iteration":291,"passed_time":2.499360665,"remaining_time":0.06847563467},
{"learn":[1177877.075],"iteration":292,"passed_time":2.508414708,"remaining_time":0.05992799645},
{"learn":[1175921.808],"iteration":293,"passed_time":2.516668189,"remaining_time":0.0513605753},
{"learn":[1172202.516],"iteration":294,"passed_time":2.525686131,"remaining_time":0.04280823951},
{"learn":[1169444.787],"iteration":295,"passed_time":2.535540651,"remaining_time":0.03426406285},
{"learn":[1167825.747],"iteration":296,"passed_time":2.544100979,"remaining_time":0.02569798969},
{"learn":[1164285.457],"iteration":297,"passed_time":2.55354747,"remaining_time":0.01713790248},
{"learn":[1160906.583],"iteration":298,"passed_time":2.561662354,"remaining_time":0.008567432622},
{"learn":[1159089.455],"iteration":299,"passed_time":2.570815501,"remaining_time":0}
]}